pymergen/__init__.py
pymergen/bin/__init__.py
pymergen/bin/runner.py
pymergen/collector/__init__.py
pymergen/collector/cgroup.py
pymergen/collector/collector.py
pymergen/collector/perf.py
pymergen/collector/process.py
pymergen/collector/thread.py
pymergen/conf/schema/schema_1.0.yaml
pymergen/conf/schema/includes/command.yaml
pymergen/conf/schema/includes/controller/cgroup.yaml
pymergen/controller/__init__.py
pymergen/controller/controller.py
pymergen/controller/factory.py
pymergen/controller/group.py
pymergen/core/__init__.py
pymergen/core/context.py
pymergen/core/executor.py
pymergen/core/logger.py
pymergen/core/parser.py
pymergen/core/process.py
pymergen/core/runner.py
pymergen/core/stat.py
pymergen/core/thread.py
pymergen/entity/__init__.py
pymergen/entity/case.py
pymergen/entity/command.py
pymergen/entity/config.py
pymergen/entity/entity.py
pymergen/entity/plan.py
pymergen/entity/suite.py
pymergen/plugin/__init__.py
pymergen/plugin/manager.py
pymergen/plugin/plugin.py
pymergen/plugin/registry.py
pymergen/plugin/collector/__init__.py
pymergen/plugin/collector/cgroup/plugin.py
pymergen/plugin/collector/cgroup/schema_1.0.yaml
pymergen/plugin/collector/command/plugin.py
pymergen/plugin/collector/command/schema_1.0.yaml
pymergen/plugin/collector/perf_profile/plugin.py
pymergen/plugin/collector/perf_profile/schema_1.0.yaml
pymergen/plugin/collector/perf_stat/plugin.py
pymergen/plugin/collector/perf_stat/schema_1.0.yaml
pymergen-0.5.0.dist-info/licenses/LICENSE
pymergen-0.5.0.dist-info/METADATA
pymergen-0.5.0.dist-info/WHEEL
pymergen-0.5.0.dist-info/top_level.txt
pymergen-0.5.0.dist-info/RECORD
