Metadata-Version: 2.4
Name: pymergen
Version: 0.5.0
Summary: PyMergen is a configuration-driven test automation tool for Linux.
Author-email: Burak Seydioglu <buraks78@gmail.com>
License-Expression: GPL-3.0-only
Project-URL: Source, https://github.com/buraks78/pymergen
Project-URL: Issues, https://github.com/buraks78/pymergen/issues
Keywords: test,benchmark,collect,perf,stat,profile,trace,cgroup,linux
Classifier: Development Status :: 3 - Alpha
Classifier: Programming Language :: Python :: 3
Classifier: Operating System :: POSIX :: Linux
Classifier: Topic :: System :: Systems Administration
Requires-Python: >=3.12
License-File: LICENSE
Requires-Dist: pyyaml
Requires-Dist: cerberus
Dynamic: license-file
